linkLists/__init__.py
linkLists/linkListStype.py
linkLists/linkListsBase.py
linkLists/linkListsManager.py
linkLists/linkListsRegister.py
linkLists/main.py
guest881_linkLists-0.2.1.dist-info/METADATA
guest881_linkLists-0.2.1.dist-info/WHEEL
guest881_linkLists-0.2.1.dist-info/top_level.txt
guest881_linkLists-0.2.1.dist-info/RECORD
