Metadata-Version: 2.1
Name: guest881-linkLists
Version: 0.2.1
Summary: 最基础的链表库，自娱自乐，目前仅支持环形链表、常规链表，新增了去重链表，修复了一些越界行为和BUG
Home-page: https://github.com/guest881/min_linkLists
Author: guest881
Author-email: axijwqmxqoxmqldnq@mzjgx.dpdns.org
License: MIT
Classifier: Programming Language :: Python :: 3
Classifier: License :: OSI Approved :: MIT License
Classifier: Operating System :: OS Independent
Requires-Python: >=3.8
